setup.py
scripts/yastatsd
yastatsd/__init__.py
yastatsd/counter.py
yastatsd/server.py
yastatsd.egg-info/PKG-INFO
yastatsd.egg-info/SOURCES.txt
yastatsd.egg-info/dependency_links.txt
yastatsd.egg-info/requires.txt
yastatsd.egg-info/top_level.txt
yastatsd/backends/__init__.py
yastatsd/backends/graphite.py