Metadata-Version: 1.0
Name: yastatsd
Version: 0.1.6
Summary: Yet Another Statsd Server
Home-page: http://github.com/greghaynes/YAStatsd
Author: Gregory Haynes
Author-email: greg@greghaynes.net
License: MIT
Platform: UNKNOWN
